Classfile /Users/aimeewang/Desktop/perf/jBProF/jbe/Test.class
  Last modified Mar 24, 2020; size 233 bytes
  SHA-256 checksum a62dd0dcde6513e723566f959085ca4df38ab0ef0291ce98f8d3dcf656860525
  Compiled from "Test.java"
public class Test
  minor version: 0
  major version: 57
  flags: (0x0021) ACC_PUBLIC, ACC_SUPER
  this_class: #7                          // Test
  super_class: #2                         // java/lang/Object
  interfaces: 0, fields: 1, methods: 1, attributes: 1
Constant pool:
   #1 = Methodref          #2.#3          // java/lang/Object."<init>":()V
   #2 = Class              #4             // java/lang/Object
   #3 = NameAndType        #5:#6          // "<init>":()V
   #4 = Utf8               java/lang/Object
   #5 = Utf8               <init>
   #6 = Utf8               ()V
   #7 = Class              #8             // Test
   #8 = Utf8               Test
   #9 = Utf8               DEFAULT
  #10 = Utf8               I
  #11 = Utf8               ConstantValue
  #12 = Integer            16
  #13 = Utf8               Code
  #14 = Utf8               LineNumberTable
  #15 = Utf8               SourceFile
  #16 = Utf8               Test.java
{
  static final int DEFAULT;
    descriptor: I
    flags: (0x0018) ACC_STATIC, ACC_FINAL
    ConstantValue: int 16

  public Test();
    descriptor: ()V
    flags: (0x0001) ACC_PUBLIC
    Code:
      stack=1, locals=1, args_size=1
         0: aload_0
         1: invokespecial #1                  // Method java/lang/Object."<init>":()V
         4: return
      LineNumberTable:
        line 1: 0
}
SourceFile: "Test.java"
